LICENSE
README.md
setup.py
ipybd/__init__.py
ipybd/core.py
ipybd.egg-info/PKG-INFO
ipybd.egg-info/SOURCES.txt
ipybd.egg-info/dependency_links.txt
ipybd.egg-info/requires.txt
ipybd.egg-info/top_level.txt
ipybd/function/api_terms.py
ipybd/function/bioname.py
ipybd/function/cleaner.py
ipybd/function/geo.py
ipybd/label/bjm_cryptoflora.css
ipybd/label/bjm_cryptoflora.mustache
ipybd/label/bjm_painting.css
ipybd/label/bjm_painting.mustache
ipybd/label/bjm_plant.css
ipybd/label/bjm_plant.mustache
ipybd/label/cryptoflora_code.css
ipybd/label/cryptoflora_code.mustache
ipybd/label/flora_code.css
ipybd/label/flora_code.mustache
ipybd/label/herb_label.py
ipybd/label/label_maker.py
ipybd/label/plant.css
ipybd/label/plant.mustache
ipybd/label/plant_en.css
ipybd/label/plant_en.mustache
ipybd/lib/admin.py
ipybd/lib/chinese_admin_div.json
ipybd/lib/noi_occurrence_schema.py
ipybd/lib/occurence_test_data.json
ipybd/lib/personal_table_map.json
ipybd/lib/std_fields_alias.json
ipybd/lib/std_options_alias.json
ipybd/occurrence/cvh.py
ipybd/occurrence/gbif.py
ipybd/occurrence/noi.py
ipybd/table/model.py
ipybd/table/terms.py