Metadata-Version: 2.1
Name: ipybd
Version: 1.4.4
Summary: Powerful data cleaner for biodiversity
Home-page: https://github.com/leisux/ipybd
Author: Xu Zhoufeng
Author-email: xu_zhoufeng@hotmail.com
License: GPL-3.0 License
Keywords: biodiversity,scientificName,herbarium,specimens,bdcleaner,labelmaker
Platform: any
Requires-Python: >=3.6.1
License-File: LICENSE
